LICENCE.txt
MANIFEST.in
README.rst
pyproject.toml
setup.cfg
setup.py
djangoapp_sample/__init__.py
djangoapp_sample/apps.py
djangoapp_sample/cms_plugins.py
djangoapp_sample/exceptions.py
djangoapp_sample/routers.py
djangoapp_sample/settings.py
djangoapp_sample/urls.py
djangoapp_sample/admin/__init__.py
djangoapp_sample/admin/article.py
djangoapp_sample/admin/blog.py
djangoapp_sample/compat/__init__.py
djangoapp_sample/compat/default_storage.py
djangoapp_sample/compat/import_zoneinfo.py
djangoapp_sample/factories/__init__.py
djangoapp_sample/factories/article.py
djangoapp_sample/factories/blog.py
djangoapp_sample/factories/user.py
djangoapp_sample/forms/__init__.py
djangoapp_sample/forms/blog.py
djangoapp_sample/migrations/0001_initial.py
djangoapp_sample/migrations/__init__.py
djangoapp_sample/models/__init__.py
djangoapp_sample/models/article.py
djangoapp_sample/models/blog.py
djangoapp_sample/plugins/__init__.py
djangoapp_sample/plugins/blog.py
djangoapp_sample/serializers/__init__.py
djangoapp_sample/serializers/article.py
djangoapp_sample/serializers/blog.py
djangoapp_sample/templates/djangoapp_sample/article_detail.html
djangoapp_sample/templates/djangoapp_sample/base.html
djangoapp_sample/templates/djangoapp_sample/blog_detail.html
djangoapp_sample/templates/djangoapp_sample/blog_index.html
djangoapp_sample/templates/djangoapp_sample/blog_plugin.html
djangoapp_sample/templates/djangoapp_sample/pagination.html
djangoapp_sample/utils/__init__.py
djangoapp_sample/utils/cms_api.py
djangoapp_sample/utils/cms_tests.py
djangoapp_sample/utils/tests.py
djangoapp_sample/views/__init__.py
djangoapp_sample/views/article.py
djangoapp_sample/views/blog.py
djangoapp_sample/viewsets/__init__.py
djangoapp_sample/viewsets/article.py
djangoapp_sample/viewsets/blog.py
djangoapp_sample/viewsets/mixins.py
sveetch_djangoapp_sample.egg-info/PKG-INFO
sveetch_djangoapp_sample.egg-info/SOURCES.txt
sveetch_djangoapp_sample.egg-info/dependency_links.txt
sveetch_djangoapp_sample.egg-info/requires.txt
sveetch_djangoapp_sample.egg-info/top_level.txt
sveetch_djangoapp_sample.egg-info/zip-safe